switchinfo/__init__.py
switchinfo/admin.py
switchinfo/apps.py
switchinfo/forms.py
switchinfo/models.py
switchinfo/urls.py
switchinfo/views.py
switchinfo/SwitchSNMP/ArubaCX.py
switchinfo/SwitchSNMP/ArubaVSF.py
switchinfo/SwitchSNMP/Cisco.py
switchinfo/SwitchSNMP/EasySNMPCompat.py
switchinfo/SwitchSNMP/Extreme.py
switchinfo/SwitchSNMP/NetSNMPCompat.py
switchinfo/SwitchSNMP/SNMPVariable.py
switchinfo/SwitchSNMP/SwitchSNMP.py
switchinfo/SwitchSNMP/__init__.py
switchinfo/SwitchSNMP/exceptions.py
switchinfo/SwitchSNMP/select.py
switchinfo/SwitchSNMP/utils.py
switchinfo/load_info/__init__.py
switchinfo/load_info/load_interfaces.py
switchinfo/load_info/load_mac.py
switchinfo/load_info/load_vlan.py
switchinfo/load_info/switch_info.py
switchinfo/management/commands/SwitchBaseCommand.py
switchinfo/management/commands/__init__.py
switchinfo/management/commands/build_groups.py
switchinfo/management/commands/load_arp.py
switchinfo/management/commands/load_arp_pfsense.py
switchinfo/management/commands/load_interfaces_rfc.py
switchinfo/management/commands/load_mac.py
switchinfo/management/commands/load_oui.py
switchinfo/management/commands/load_vlans.py
switchinfo/management/commands/switch_info.py
switchinfo/management/commands/switch_update.py
switchinfo/migrations/0001_initial.py
switchinfo/migrations/0002_switch_location.py
switchinfo/migrations/0003_switchgroup.py
switchinfo/migrations/__init__.py
switchinfo/static/switchinfo/menu.css
switchinfo/static/switchinfo/switchinfo.css
switchinfo/static/switchinfo/switchinfo_fancy.css
switchinfo/templates/switchinfo/base.html
switchinfo/templates/switchinfo/models.html
switchinfo/templates/switchinfo/search.html
switchinfo/templates/switchinfo/switch.html
switchinfo/templates/switchinfo/switch_list.html
switchinfo/templates/switchinfo/switch_table.html
switchinfo/templates/switchinfo/switches.html
switchinfo/templates/switchinfo/switches_group.html
switchinfo/templates/switchinfo/vlan.html
switchinfo-1.6.dist-info/LICENSE
switchinfo-1.6.dist-info/METADATA
switchinfo-1.6.dist-info/WHEEL
switchinfo-1.6.dist-info/top_level.txt
switchinfo-1.6.dist-info/RECORD
