Metadata-Version: 2.1
Name: switchinfo
Version: 1.6
Summary: A tool to show what is connected to switch ports
Home-page: https://github.com/datagutten/switchinfo
Author: Anders Birkenes
Author-email: datagutten@datagutten.net
License: GPL
Platform: UNKNOWN
Classifier: Framework :: Django
Classifier: Framework :: Django :: 2.1
Classifier: Intended Audience :: System Administrators
Classifier: Intended Audience :: Telecommunications Industry
Classifier: License :: OSI Approved :: GNU General Public License v3 or later (GPLv3+)
Classifier: Operating System :: OS Independent
Classifier: Programming Language :: Python
Classifier: Programming Language :: Python :: 3.6
Classifier: Programming Language :: Python :: 3.7
License-File: LICENSE
Requires-Dist: django
Requires-Dist: requests
